faststan/__init__.py
faststan/cli/__init__.py
faststan/cli/nats.py
faststan/cli/services.py
faststan/cli/stan.py
faststan/cli/subscriptions.py
faststan/inspect.py
faststan/models.py
faststan/nats.py
faststan/publisher.py
faststan/service.py
faststan/settings.py
faststan/stan.py
faststan/subscriber.py
faststan/utils.py
faststan/wrappers/__init__.py
faststan/wrappers/reply.py
faststan/wrappers/subscribe.py
faststan-0.20.0.dist-info/entry_points.txt
faststan-0.20.0.dist-info/WHEEL
faststan-0.20.0.dist-info/METADATA
faststan-0.20.0.dist-info/RECORD
