Metadata-Version: 2.1
Name: faststan
Version: 0.20.0
Summary: Build data streaming pipelines using NATS or NATS streaming
Home-page: https://pypi.org/project/faststan/
License: MIT
Author: gcharbon
Author-email: guillaume.charbonnier@capgemini.com
Requires-Python: >=3.7,<4.0
Classifier: License :: OSI Approved :: MIT License
Classifier: Programming Language :: Python :: 3
Classifier: Programming Language :: Python :: 3.7
Classifier: Programming Language :: Python :: 3.8
Classifier: Programming Language :: Python :: 3.9
Requires-Dist: asyncio-nats-client (>=0.10.0,<0.11.0)
Requires-Dist: asyncio-nats-streaming (>=0.4.0,<0.5.0)
Requires-Dist: loguru (>=0.5.3,<0.6.0)
Requires-Dist: pydantic (>=1.6,<2.0)
Requires-Dist: returns (>=0.14.0,<0.15.0)
Requires-Dist: typer (>=0.3.2,<0.4.0)
Project-URL: Repository, https://gitlab.com/faststan/faststan.git
